Yum4FIT_halfdeadpie-0.3.6.1.dist-info/DESCRIPTION.rst
Yum4FIT_halfdeadpie-0.3.6.1.dist-info/METADATA
Yum4FIT_halfdeadpie-0.3.6.1.dist-info/RECORD
Yum4FIT_halfdeadpie-0.3.6.1.dist-info/WHEEL
Yum4FIT_halfdeadpie-0.3.6.1.dist-info/dependency_links.txt
Yum4FIT_halfdeadpie-0.3.6.1.dist-info/entry_points.txt
Yum4FIT_halfdeadpie-0.3.6.1.dist-info/metadata.json
Yum4FIT_halfdeadpie-0.3.6.1.dist-info/top_level.txt
yum/CONSTANTS.py
yum/Guest.py
yum/Parser.py
yum/__init__.py
yum/__main__.py
yum/account.py
yum/cli.py
yum/connector.py
yum/food.py
yum/gui.py
yum/mainwindow.ui
yum/profile.py
yum/state.py
yum/unity.py
yum/web.py
yum/yum.py
yum/static/first.jpg
yum/static/second.jpg
yum/static/style.css
yum/templates/error.html
yum/templates/header.html
yum/templates/index.html
yum/templates/layout.html
