Metadata-Version: 2.0
Name: Yum4FIT-halfdeadpie
Version: 0.3.6.1
Summary: Level up in your cooking skills
Home-page: https://github.com/HalfDeadPie/Yum4FIT
Author: Simon Stefunko
Author-email: s.stefunko@gmail.com
License: Public Domain
Keywords: food,yummly,instagram,recipes,game
Platform: UNKNOWN
Classifier: Intended Audience :: Developers
Classifier: License :: Public Domain
Classifier: Programming Language :: Python
Classifier: Programming Language :: Python :: 3
Classifier: Programming Language :: Python :: 3.6
Classifier: Topic :: Software Development :: Libraries
Classifier: Framework :: Flask
Classifier: Environment :: Console
Classifier: Environment :: Web Environment
Requires-Python: ~=3.6
Requires-Dist: Flask
Requires-Dist: click (>=6)
Requires-Dist: requests (>=2.11.1)
Requires-Dist: pyqt5-tools
Requires-Dist: InstagramAPI
Requires-Dist: PyQt5
